{
  "assetSlug": "ondo-ousg",
  "assetSymbol": "OUSG",
  "assetName": "Ondo Short-Term US Government Treasuries",
  "monitoringStatus": "active-analytics",
  "monitoringPriority": "medium",
  "gradeBaseline": {
    "grade": "analytics",
    "score": 82,
    "baselineDate": "2026-06-01",
    "baselineFile": "grade-baseline.json"
  },
  "reviewSchedule": {
    "lastManualReview": "2026-06-01",
    "nextManualReview": "2026-07-01",
    "manualReviewFrequencyDays": 30,
    "marketRefreshFrequencyHours": 24,
    "liquidityRefreshFrequencyHours": 24,
    "sourceHealthCheckFrequencyDays": 7,
    "legalReviewFrequencyDays": 60,
    "riskReviewFrequencyDays": 30
  },
  "freshnessPolicy": {
    "marketDataMaxAgeHours": 24,
    "liquidityDataMaxAgeHours": 24,
    "holderDataMaxAgeDays": 7,
    "sourceDataMaxAgeDays": 30,
    "legalDataMaxAgeDays": 60,
    "riskDataMaxAgeDays": 30
  },
  "autoMonitoredFields": [
    {
      "layer": "market",
      "field": "price",
      "source": "CoinGecko",
      "sourceUrl": "coingecko",
      "refreshFrequencyHours": 24
    },
    {
      "layer": "market",
      "field": "marketCap",
      "source": "CoinGecko",
      "sourceUrl": "coingecko",
      "refreshFrequencyHours": 24
    },
    {
      "layer": "market",
      "field": "volume24h",
      "source": "CoinGecko",
      "sourceUrl": "coingecko",
      "refreshFrequencyHours": 24
    },
    {
      "layer": "market",
      "field": "holderCount",
      "source": "Etherscan",
      "sourceUrl": "etherscan",
      "refreshFrequencyDays": 7
    }
  ],
  "manualMonitoredFields": [
    {
      "layer": "compliance",
      "field": "legalOpinionUrl",
      "status": "missing",
      "importance": "warning",
      "notes": "Search for public legal opinion or legal document URL."
    },
    {
      "layer": "reserve",
      "field": "lastAuditUrl",
      "status": "missing",
      "importance": "warning",
      "notes": "Find official audit/report URL if available."
    },
    {
      "layer": "risk",
      "field": "holderConcentration",
      "status": "needs-analysis",
      "importance": "warning",
      "notes": "Analyze top-holder concentration, exchange wallets, treasury/team wallets, and labeled-wallet distribution."
    },
    {
      "layer": "liquidity",
      "field": "bidAskSpread",
      "status": "needs-analysis",
      "importance": "warning",
      "notes": "Check exchange order books and DEX price impact before improving liquidity score."
    },
    {
      "layer": "reserve",
      "field": "reserveBreakdown",
      "status": "manual-verification-required",
      "importance": "warning",
      "notes": "Exact reserve percentages were removed; official docs support high-level backing/fund investment description only. Refresh manually if a stable dated composition source is found."
    },
    {
      "layer": "compliance",
      "field": "blockedJurisdictions",
      "status": "verified-official-docs",
      "importance": "warning",
      "notes": "Updated to official OUSG Eligibility jurisdictional restrictions source; monitor manually for legal/source changes."
    }
  ],
  "knownBlockers": [],
  "knownWarnings": [
    "Missing legal opinion or legal document URL",
    "No proof-of-reserves confirmed",
    "Missing audit/report URL",
    "Missing on-chain liquidity"
  ],
  "alertRules": [
    {
      "id": "market-data-stale",
      "severity": "warning",
      "condition": "market.lastUpdated older than freshnessPolicy.marketDataMaxAgeHours",
      "action": "Refresh market data from configured market sources."
    },
    {
      "id": "liquidity-drop",
      "severity": "warning",
      "condition": "liquidity.onchainLiquidity drops by more than 30% from baseline snapshot",
      "action": "Review DEX/CEX liquidity sources before changing liquidityScore."
    },
    {
      "id": "source-conflict",
      "severity": "info",
      "condition": "primary and cross-check market sources differ materially",
      "action": "Keep conflict note and prefer primary source unless methodology changes."
    },
    {
      "id": "new-legal-evidence-found",
      "severity": "review_required",
      "condition": "legal opinion, regulator filing, or official issuer document is found",
      "action": "Reassess compliance, institutional, reserve, and risk layers."
    },
    {
      "id": "audit-evidence-found",
      "severity": "review_required",
      "condition": "official external smart-contract audit or security review is found",
      "action": "Update blockchain, sources, and smartContractRisk score."
    }
  ],
  "sourceHealthChecks": [
    {
      "name": "Official website",
      "url": "https://ondo.finance/ousg",
      "tier": "Tier 1",
      "frequencyDays": 7
    },
    {
      "name": "Official docs",
      "url": "https://docs.ondo.finance/ondo-global-markets/trust-and-transparency",
      "tier": "Tier 1",
      "frequencyDays": 7
    },
    {
      "name": "Official social",
      "url": "https://x.com/OndoFinance",
      "tier": "Tier 3",
      "frequencyDays": 30
    },
    {
      "name": "identity.launchDate",
      "url": "https://www.coingecko.com/en/coins/ousg",
      "tier": "Tier 2",
      "frequencyDays": 30
    },
    {
      "name": "reserve.custodian",
      "url": "https://docs.ondo.finance/trust-and-security",
      "tier": "Tier 1",
      "frequencyDays": 30
    },
    {
      "name": "reserve.reserveBreakdown",
      "url": "https://docs.ondo.finance/trust-and-security",
      "tier": "Tier 1",
      "frequencyDays": 90,
      "status": "official-docs-high-level-only"
    },
    {
      "name": "compliance.blockedJurisdictions",
      "url": "https://docs.ondo.finance/qualified-access-products/eligibility",
      "tier": "Tier 1",
      "frequencyDays": 90
    },
    {
      "name": "blockchain.contractAddress",
      "url": "https://docs.ondo.finance/addresses",
      "tier": "Tier 1",
      "frequencyDays": 30
    }
  ],
  "monitoringNotes": [
    "Generated from ondo-ousg asset layer files.",
    "Review manually before treating this as a production monitoring profile.",
    "Do not overwrite asset-specific analyst notes without checking source-discovery.md and grade-baseline.json.",
    "reserve.reserveBreakdown remains manual-required because exact percentages were removed; compliance.blockedJurisdictions now points to the official OUSG Eligibility page."
  ],
  "templateVersion": 1
}
